Workbook
Name AllFields: [1]Conversions!$A$2:$A$78
Name AllFields: [1]Conversions!$A$2:$A$78

Sheet Change History
B2: Version | C2: Change Owner | D2: Date | E2: Change Description
B3: 1 | C3: E2open | D3: 45089 | E3: Initial Release

Sheet Mapping
A2: Final TARGET CDM MTIMShipmentLot-1.0 | G2: INTERNAL E2OPEN (IDM/OAGIS) | I2: SOURCE X12 856 4010
A3: Level | B3: Index | C3: DESCRIPTION / VALUE | D3: SEGMENT / FIELD XPATH | E3: CONDITION | F3: M/O Usage | G3: XPATH | H3: CONDITION | I3: DESCRIPTION/VALUE | J3: SEGMENT / FIELD XPATH | K3: CONDITION | L3: Note
B4: =VLOOKUP(C4,MtimShipmentLot!B4:C384,2,0) -> 0 | C4: ShipmentId | D4: Shipment ID | F4: Yes | J4: /X12/TS_856/BSN/BSN02
B5: =VLOOKUP(C5,MtimShipmentLot!B5:C385,2,0) -> 1 | C5: CustomerName | D5: Customer ID | F5: Yes | J5: /X12/TS_856/GROUP_1[HL/HL03='S']/GROUP_4/N1[N101 = "LW" and N103 = "ZZ"]/N104
B6: =VLOOKUP(C6,MtimShipmentLot!B6:C386,2,0) -> 2 | C6: CustomerDescription | D6: Customer Description | F6: No | J6: /X12/TS_856/GROUP_1[HL/HL03='S']/GROUP_4/N1[N101 = "LW"]/N102
B7: =VLOOKUP(C7,MtimShipmentLot!B7:C387,2,0) -> 5 | C7: CustomerAddressDescriptor | D7: Customer Address - Descriptor | F7: No | J7: /X12/TS_856/GROUP_1[HL/HL03='S']/GROUP_4/N2[N1/N101 = "LW"]/N201
B8: =VLOOKUP(C8,MtimShipmentLot!B8:C388,2,0) -> 6 | C8: CustomerAddress1 | D8: Customer Address 1 | F8: No | J8: /X12/TS_856/GROUP_1[HL/HL03='S']/GROUP_4/N2[N1/N101 = "LW"]/N202
B9: =VLOOKUP(C9,MtimShipmentLot!B9:C389,2,0) -> 7 | C9: CustomerAddress2 | D9: Customer Address 2 | F9: No | J9: /X12/TS_856/GROUP_1[HL/HL03='S']/GROUP_4/N3[N1/N101 = "LW"]/N301
B10: =VLOOKUP(C10,MtimShipmentLot!B10:C390,2,0) -> 8 | C10: CustomerAddress3 | D10: Customer Address 3 | F10: No | J10: /X12/TS_856/GROUP_1[HL/HL03='S']/GROUP_4/N3[N1/N101 = "LW"]/N302
B11: =VLOOKUP(C11,MtimShipmentLot!B11:C391,2,0) -> 11 | C11: CustomerAddressCity | D11: Customer City | F11: No | J11: /X12/TS_856/GROUP_1[HL/HL03='S']/GROUP_4/N4[N1/N101 = "LW"]/N401
B12: =VLOOKUP(C12,MtimShipmentLot!B12:C392,2,0) -> 13 | C12: CustomerAddressState | D12: Customer State | F12: No | J12: /X12/TS_856/GROUP_1[HL/HL03='S']/GROUP_4/N4[N1/N101 = "LW"]/N402
B13: =VLOOKUP(C13,MtimShipmentLot!B13:C393,2,0) -> 14 | C13: CustomerAddressCountry | D13: Customer Country | F13: No | J13: /X12/TS_856/GROUP_1[HL/HL03='S']/GROUP_4/N4[N1/N101 = "LW"]/N404
B14: =VLOOKUP(C14,MtimShipmentLot!B14:C394,2,0) -> 15 | C14: CustomerAddressZip | D14: Customer Zip | F14: No | J14: /X12/TS_856/GROUP_1[HL/HL03='S']/GROUP_4/N4[N1/N101 = "LW"]/N403
B15: =VLOOKUP(C15,MtimShipmentLot!B15:C395,2,0) -> 16 | C15: SupplierName | D15: Supplier ID | F15: Yes | J15: /X12/TS_856/GROUP_1[HL/HL03='S']/GROUP_4/N1[N101 = "SU" and N103 = "ZZ"]/N104
... B24: =VLOOKUP(C24,MtimShipmentLot!B24:C404,2,0) -> 30 | C24: SupplierAddressZip | D24: Supplier Zip | F24: No | J24: /X12/TS_856/GROUP_1[HL/HL03='S']/GROUP_4/N4[N1/N101 = "SU"]/N403
B25: =VLOOKUP(C25,MtimShipmentLot!B25:C405,2,0) -> 31 | C25: ShipmentCreationDate | D25: Shipment Creation Date | E25: YYYY-MM-DDTHH:MM:SS+0000 | F25: No | J25: concat(/X12/TS_856/BSN/BSN03, /X12/TS_856/BSN/BSN04) | L25: BSN03: CCYYMMDD BSN04: HHMMSS
B26: =VLOOKUP(C26,MtimShipmentLot!B26:C406,2,0) -> 33 | C26: ShipmentStatus | D26: Shipment Status | F26: No
B27: =VLOOKUP(C27,MtimShipmentLot!B27:C407,2,0) -> 34 | C27: ShipmentDate | D27: Shipment Date | E27: YYYY-MM-DDTHH:MM:SS+0000 | F27: Yes | J27: /X12/TS_856/GROUP_1[HL/HL03='S']/DTM[DTM01 = "011"]/DTM02 | L27: DTM02: CCYYMMDD DTM03: HHMM
B28: =VLOOKUP(C28,MtimShipmentLot!B28:C408,2,0) -> 35 | C28: PlannedDeliveryDate | D28: Planned Delivery Date | E28: YYYY-MM-DDTHH:MM:SS+0000 | F28: Yes | J28: /X12/TS_856/GROUP_1[HL/HL03='S']/DTM[DTM01 = "017"]/DTM02 | L28: DTM02: CCYYMMDD DTM03: HHMM
B29: =VLOOKUP(C29,MtimShipmentLot!B29:C409,2,0) -> 36 | C29: ETAAtFinalSite | D29: Final Site ETA | E29: YYYY-MM-DDTHH:MM:SS+0000 | F29: No | J29: /X12/TS_856/GROUP_1[HL/HL03='S']/DTM[DTM01 = "371"]/DTM02 | L29: DTM02: CCYYMMDD
B30: =VLOOKUP(C30,MtimShipmentLot!B30:C410,2,0) -> 37 | C30: LastKnownMilestone | D30: Last Known Milestone | F30: No | J30: /X12/TS_856/GROUP_1[HL/HL03='S']/REF[REF01 = "76"]/REF02
B31: =VLOOKUP(C31,MtimShipmentLot!B31:C411,2,0) -> 38 | C31: ArrivalAtLastKnownMilestone | D31: Last Known Milestone Arrival | E31: YYYY-MM-DDTHH:MM:SS+0000 | F31: No | J31: /X12/TS_856/GROUP_1[HL/HL03='S']/DTM[DTM01 = "372"]/DTM02 | L31: DTM02: CCYYMMDD
B32: =VLOOKUP(C32,MtimShipmentLot!B32:C412,2,0) -> 39 | C32: DepartureFromLastKnownMilestone | D32: Last Known Milestone Departure | E32: YYYY-MM-DDTHH:MM:SS+0000 | F32: No | J32: /X12/TS_856/GROUP_1[HL/HL03='S']/DTM[DTM01 = "370"]/DTM02 | L32: DTM02: CCYYMMDD
B33: =VLOOKUP(C33,MtimShipmentLot!B33:C413,2,0) -> 40 | C33: CarrierName | D33: Carrier | F33: No | J33: /X12/TS_856/GROUP_1[HL/HL03='S']/TD5[TD501 = "B" and TD502 = "ZZ"]/TD503
B34: =VLOOKUP(C34,MtimShipmentLot!B34:C414,2,0) -> 41 | C34: ShipmentMode | D34: Shipment Mode | F34: No | J34: /X12/TS_856/GROUP_1[HL/HL03='S']/TD5[TD501 = "B"]/TD504 | K34: Lookup source in "Mode/Transportation Mode" table
B35: =VLOOKUP(C35,MtimShipmentLot!B35:C415,2,0) -> 42 | C35: WaybillNumber | D35: Waybill # | F35: No | J35: /X12/TS_856/GROUP_1[HL/HL03='S']/REF[REF01 = "WY"]/REF02
B36: =VLOOKUP(C36,MtimShipmentLot!B36:C416,2,0) -> 43 | C36: ShipmentDeliveryBOLNumber | D36: Shipment Delivery BOL # | F36: No | J36: /X12/TS_856/GROUP_1[HL/HL03='S']/REF[REF01 = "BM"]/REF02
B37: =VLOOKUP(C37,MtimShipmentLot!B37:C417,2,0) -> 44 | C37: PackingSlipNumber | D37: Packing Slip # | F37: No | J37: /X12/TS_856/GROUP_1[HL/HL03='S']/REF[REF01 = "PK"]/REF02
B38: =VLOOKUP(C38,MtimShipmentLot!B38:C418,2,0) -> 45 | C38: CarrierReferenceNumber | D38: Carrier Reference # | F38: No | J38: /X12/TS_856/GROUP_1[HL/HL03='S']/REF[REF01 = "ZH"]/REF02
B39: =VLOOKUP(C39,MtimShipmentLot!B39:C419,2,0) -> 46 | C39: ShipperReferenceNumber | D39: Shipper Reference # | F39: No | J39: /X12/TS_856/GROUP_1[HL/HL03='S']/REF[REF01 = "SI"]/REF02
B40: =VLOOKUP(C40,MtimShipmentLot!B40:C420,2,0) -> 47 | C40: ShipToLocationType | D40: Ship To Type (Site/Hub) | F40: Yes | K40: HardCode to "Site"
B41: =VLOOKUP(C41,MtimShipmentLot!B41:C421,2,0) -> 48 | C41: CountryOfOrigin | D41: Country Of Origin | F41: No | J41: /X12/TS_856/GROUP_1[HL/HL03='S']/REF[REF01 = "4B"]/REF02
B42: =VLOOKUP(C42,MtimShipmentLot!B42:C422,2,0) -> 49 | C42: NumberOfPackages | D42: Number Of Packages | F42: No | J42: /X12/TS_856/GROUP_1[HL/HL03='S']/TD1[TD101 = "PKG"]/TD102
B43: =VLOOKUP(C43,MtimShipmentLot!B43:C423,2,0) -> 51 | C43: ImporterOfRecordNumber | D43: Importer Of Record Number | F43: No | J43: /X12/TS_856/GROUP_1[HL/HL03='S']/REF[REF01 = "IRN"]/REF02
B44: =VLOOKUP(C44,MtimShipmentLot!B44:C424,2,0) -> 52 | C44: ConsigneeNumber | D44: Consignee # | F44: No | J44: /X12/TS_856/GROUP_1[HL/HL03='S']/REF[REF01 = "6A"]/REF02
B45: =VLOOKUP(C45,MtimShipmentLot!B45:C425,2,0) -> 54 | C45: PlaceOfDelivery | D45: Place Of Delivery | F45: No | J45: /X12/TS_856/GROUP_1[HL/HL03='S']/TD5[TD501 = "B"and TD507 = "PL"]/TD508
B46: =VLOOKUP(C46,MtimShipmentLot!B46:C426,2,0) -> 55 | C46: ShipToSite | D46: Ship To Site | F46: Yes | J46: /X12/TS_856/GROUP_1[HL/HL03='S']/GROUP_4/N1[N101 = "ST"and N103 = "ZZ"]/N104
B47: =VLOOKUP(C47,MtimShipmentLot!B47:C427,2,0) -> 56 | C47: ShipToPartyName | D47: Ship-to-Party Name | F47: No | J47: /X12/TS_856/GROUP_1[HL/HL03='S']/GROUP_4/N1[N101 = "ST"]/N102
B48: =VLOOKUP(C48,MtimShipmentLot!B48:C428,2,0) -> 58 | C48: ShipToAddressDescriptor | D48: Ship To Address - Descriptor | F48: No | J48: /X12/TS_856/GROUP_1[HL/HL03='S']/GROUP_4/N2[N101 = "ST"]/N201
B49: =VLOOKUP(C49,MtimShipmentLot!B49:C429,2,0) -> 59 | C49: ShipToAddress1 | D49: Ship To Address 1 | F49: No | J49: /X12/TS_856/GROUP_1[HL/HL03='S']/GROUP_4/N2[N101 = "ST"]/N202
B50: =VLOOKUP(C50,MtimShipmentLot!B50:C430,2,0) -> 60 | C50: ShipToAddress2 | D50: Ship To Address 2 | F50: No | J50: /X12/TS_856/GROUP_1[HL/HL03='S']/GROUP_4/N3[N101 = "ST"]/N301
B51: =VLOOKUP(C51,MtimShipmentLot!B51:C431,2,0) -> 61 | C51: ShipToAddress3 | D51: Ship To Address 3 | F51: No | J51: /X12/TS_856/GROUP_1[HL/HL03='S']/GROUP_4/N3[N101 = "ST"]/N302
B52: =VLOOKUP(C52,MtimShipmentLot!B52:C432,2,0) -> 64 | C52: ShipToAddressCity | D52: Ship To City | F52: No | J52: /X12/TS_856/GROUP_1[HL/HL03='S']/GROUP_4/N4[N101 = "ST"]/N401
... B73: =VLOOKUP(C73,MtimShipmentLot!B73:C453,2,0) -> 92 | C73: BillToAddressZip | D73: Bill To Zip | F73: No | J73: /X12/TS_856/GROUP_1[HL/HL03='S']/GROUP_4/N4[N101 = "BT"]/N403
B74: =VLOOKUP(C74,MtimShipmentLot!B74:C454,2,0) -> 105 | C74: BookingPartyAddressZip | D74: Booking Party Zip | F74: No
B75: =VLOOKUP(C75,MtimShipmentLot!B75:C455,2,0) -> 130 | C75: ShipmentLineItemId | D75: Shipment Line ID | F75: Yes | J75: /X12/TS_856/GROUP_1[HL/HL03='I']/LIN/LIN01
B76: =VLOOKUP(C76,MtimShipmentLot!B76:C456,2,0) -> 131 | C76: ShipmentLineStatus | D76: Shipment Line Status | F76: No
B77: =VLOOKUP(C77,MtimShipmentLot!B77:C457,2,0) -> 132 | C77: Action | D77: Action | F77: Yes | K77: Hardcode to InsertOrUpdate
B78: =VLOOKUP(C78,MtimShipmentLot!B78:C458,2,0) -> 135 | C78: SupplierItemName | D78: Supplier Part Number | F78: Yes | J78: /X12/TS_856/GROUP_1[HL/HL03='I']/LIN[LIN06 = "VP"]/LIN07
B79: =VLOOKUP(C79,MtimShipmentLot!B79:C459,2,0) -> 136 | C79: SupplierItemDescription | D79: Supplier Part Description | F79: No | J79: /X12/TS_856/GROUP_1[HL/HL03='I']/LIN[LIN08 = "PD"]/LIN09
B80: =VLOOKUP(C80,MtimShipmentLot!B80:C460,2,0) -> 138 | C80: ShippedQuantity | D80: Shipped Quantity | F80: Yes | J80: /X12/TS_856/GROUP_1[HL/HL03='I']/SN1/SN102
B81: =VLOOKUP(C81,MtimShipmentLot!B81:C461,2,0) -> 139 | C81: UnitOfMeasure | D81: Unit Of Measure | F81: No | J81: /X12/TS_856/GROUP_1[HL/HL03='I']/SN1/SN103
B82: =VLOOKUP(C82,MtimShipmentLot!B82:C462,2,0) -> 140 | C82: FreightCost | D82: Freight Cost | F82: No | J82: /X12/TS_856/GROUP_1[HL/HL03='I']/REF[REF01 = "91"]/REF02
B83: =VLOOKUP(C83,MtimShipmentLot!B83:C463,2,0) -> 141 | C83: Currency | D83: Currency | F83: No | J83: /X12/TS_856/GROUP_1[HL/HL03='I']/CUR[CUR01 = "LW"]/CUR02
B84: =VLOOKUP(C84,MtimShipmentLot!B84:C464,2,0) -> 144 | C84: NumberOfBoxes | D84: # Of Boxes | F84: No | J84: /X12/TS_856/GROUP_1[HL/HL03='I']/TD1[TD101 = "BOX"]/TD102
B85: =VLOOKUP(C85,MtimShipmentLot!B85:C465,2,0) -> 146 | C85: CommodityHTS-6 | D85: Commodity HTS-6 | F85: No | J85: /X12/TS_856/GROUP_1[HL/HL03='I']/TD1[TD101 = "BOX" and TD103='A']/TD104
B86: =VLOOKUP(C86,MtimShipmentLot!B86:C466,2,0) -> 147 | C86: ManufacturerName | D86: Manufacturer Name | F86: No | J86: /X12/TS_856/GROUP_1[HL/HL03='I']/GROUP_4/N1[N101 = "MF"]/N102
B87: =VLOOKUP(C87,MtimShipmentLot!B87:C467,2,0) -> 149 | C87: ManufacturerAddressDescriptor | D87: Manufacturer Address - Descriptor | F87: No | J87: /X12/TS_856/GROUP_1[HL/HL03='I']/GROUP_4/N2[N101 = "MF"]/N201
B88: =VLOOKUP(C88,MtimShipmentLot!B88:C468,2,0) -> 150 | C88: ManufacturerAddress1 | D88: Manufacturer Address 1 | F88: No | J88: /X12/TS_856/GROUP_1[HL/HL03='I']/GROUP_4/N2[N101 = "MF"]/N202
B89: =VLOOKUP(C89,MtimShipmentLot!B89:C469,2,0) -> 151 | C89: ManufacturerAddress2 | D89: Manufacturer Address 2 | F89: No | J89: /X12/TS_856/GROUP_1[HL/HL03='I']/GROUP_4/N3[N101 = "MF"]/N301
... B94: =VLOOKUP(C94,MtimShipmentLot!B94:C474,2,0) -> 159 | C94: ManufacturerAddressZip | D94: Manufacturer Zip | F94: No | J94: /X12/TS_856/GROUP_1[HL/HL03='I']/GROUP_4/N4[N101 = "MF"]/N403
B95: =VLOOKUP(C95,MtimShipmentLot!B95:C475,2,0) -> 188 | C95: RefdOrderType | D95: Ref Order Type | F95: No | K95: Hardcode to "DiscreteOrder"
B96: =VLOOKUP(C96,MtimShipmentLot!B96:C476,2,0) -> 189 | C96: RefdOrderNumber | D96: Ref Order ID | F96: Yes | J96: /X12/TS_856/GROUP_1[HL/HL03='I']/LIN[LIN10 = "PO"]/LIN11
B97: =VLOOKUP(C97,MtimShipmentLot!B97:C477,2,0) -> 190 | C97: RefdOrderLineId | D97: Ref Order Line ID | F97: Yes | J97: /X12/TS_856/GROUP_1[HL/HL03='I']/LIN[LIN12 = "PL"]/LIN13
B98: =VLOOKUP(C98,MtimShipmentLot!B98:C478,2,0) -> 191 | C98: RefdOrderScheduleId | D98: Ref Order Request ID | F98: Yes | K98: Hardcode to '1'
B99: =VLOOKUP(C99,MtimShipmentLot!B99:C479,2,0) -> 192 | C99: RefdOrderPromiseScheduleId | D99: Ref Order Promise ID | F99: No | J99: /X12/TS_856/GROUP_1[HL/HL03='I']/LIN[LIN14 = "A7"]/LIN15
B100: =VLOOKUP(C100,MtimShipmentLot!B100:C480,2,0) -> 193 | C100: FlexAttrStringLine1 | D100: Part Number (HCL) | F100: No | J100: /X12/TS_856/GROUP_1[HL/HL03='I']/LIN[LIN02 = "BP"]/LIN03
B101: =VLOOKUP(C101,MtimShipmentLot!B101:C481,2,0) -> 194 | C101: FlexAttrStringLine2 | D101: Part Description (HCL) | F101: No | J101: /X12/TS_856/GROUP_1[HL/HL03='I']/LIN[LIN04 = "GE"]/LIN05
B102: =VLOOKUP(C102,MtimShipmentLot!B102:C482,2,0) -> 326 | C102: SerialNumber | D102: Serial Number | F102: No | J102: /X12/TS_856/GROUP_1[HL/HL03='UT']/REF[REF01 = "SE"]/REF02
B103: =VLOOKUP(C103,MtimShipmentLot!B103:C483,2,0) -> 327 | C103: BatchNumber | D103: Asset Tag Number | F103: No | J103: /X12/TS_856/GROUP_1[HL/HL03='UT']/REF[REF01 = "JH"]/REF02

Sheet LookUp Table
B1: Mode/Transportation Mode
B2: Key | C2: Value
B3: A | C3: AIR
B4: AC | C4: AIR
B5: AE | C5: AIR
B6: AF | C6: AIR
B7: AH | C7: AIR
B8: FA | C8: AIR
B9: PA | C9: AIR
B10: D | C10: PARCEL
B11: U | C11: PARCEL
B12: R | C12: RAIL
B13: PR | C13: RAIL
... B36: LT | C36: LCL

Sheet CDM Sample
A1: Display all the fields in CDM output - even not mapped
A2: #0 | B2: 1 | C2: 2 | D2: 5 | E2: 6 | F2: 7 | G2: 8 | H2: 11 | I2: 13 | J2: 14 | K2: 15 | L2: 16 | M2: 17 | N2: 20 | O2: 21 | P2: 22 | Q2: 23 | R2: 26 | S2: 28 | T2: 29 | U2: 30 | V2: 31 | W2: 33 | X2: 34 | Y2: 35 | Z2: 36 | AA2: 37 | AB2: 38 | AC2: 39 | AD2: 40 | AE2: 41 | AF2: 42 | AG2: 43 | AH2: 44 | AI2: 45 | AJ2: 46 | AK2: 47 | AL2: 48 | AM2: 49 | AN2: 51 | AO2: 52 | AP2: 54 | AQ2: 55 | AR2: 56 | AS2: 58 | AT2: 59 | AU2: 60 | AV2: 61 | AW2: 64 | AX2: 66 | AY2: 67 | AZ2: 68 | BA2: 69 | BB2: 70 | BC2: 71 | BD2: 72 | BE2: 73 | BF2: 76 | BG2: 78 | BH2: 79 | BI2: 80 | BJ2: 81 | BK2: 82 | BL2: 83 | BM2: 84 | BN2: 85 | BO2: 88 | BP2: 90 | BQ2: 91 | BR2: 92 | BS2: 105 | BT2: 130 | BU2: 131 | BV2: 132 | BW2: 135 | BX2: 136 | BY2: 138 | BZ2: 139 | CA2: 140 | CB2: 141 | CC2: 144 | CD2: 146 | CE2: 147 | CF2: 149 | CG2: 150 | CH2: 151 | CI2: 152 | CJ2: 155 | CK2: 157 | CL2: 158 | CM2: 159 | CN2: 188 | CO2: 189 | CP2: 190 | CQ2: 191 | CR2: 192 | CS2: 193 | CT2: 194 | CU2: 326 | CV2: 327
A3: #Shipment ID | B3: Customer ID | C3: Customer Description | D3: Customer Address - Descriptor | E3: Customer Address 1 | F3: Customer Address 2 | G3: Customer Address 3 | H3: Customer City | I3: Customer State | J3: Customer Country | K3: Customer Zip | L3: Supplier ID | M3: Supplier Description | N3: Supplier Address - Descriptor | O3: Supplier Address 1 | P3: Supplier Address 2 | Q3: Supplier Address 3 | R3: Supplier City | S3: Supplier State | T3: Supplier Country | U3: Supplier Zip | V3: Shipment Creation Date | W3: Shipment Status | X3: Shipment Date | Y3: Planned Delivery Date | Z3: Final Site ETA | AA3: Last Known Milestone | AB3: Last Known Milestone Arrival | AC3: Last Known Milestone Departure | AD3: Carrier | AE3: Shipment Mode | AF3: Waybill # | AG3: Shipment Delivery BOL # | AH3: Packing Slip # | AI3: Carrier Reference # | AJ3: Shipper Reference # | AK3: Ship To Type (Site/Hub) | AL3: Country Of Origin | AM3: Number Of Packages | AN3: Importer Of Record Number | AO3: Consignee # | AP3: Place Of Delivery | AQ3: Ship To Site | AR3: Ship-to-Party Name | AS3: Ship To Address - Descriptor | AT3: Ship To Address 1 | AU3: Ship To Address 2 | AV3: Ship To Address 3 | AW3: Ship To City | AX3: Ship To State | AY3: Ship To Country | AZ3: Ship To Zip | BA3: Supplier Site | BB3: Ship From Address - Descriptor | BC3: Ship From Address 1 | BD3: Ship From Address 2 | BE3: Ship From Address 3 | BF3: Ship From City | BG3: Ship From State | BH3: Ship From Country | BI3: Ship From Zip | BJ3: Bill To | BK3: Bill To Address - Descriptor | BL3: Bill To Address 1 | BM3: Bill To Address 2 | BN3: Bill To Address 3 | BO3: Bill To City | BP3: Bill To State | BQ3: Bill To Country | BR3: Bill To Zip | BS3: Booking Party Zip | BT3: Shipment Line ID | BU3: Shipment Line Status | BV3: Action | BW3: Supplier Part Number | BX3: Supplier Part Description | BY3: Shipped Quantity | BZ3: Unit Of Measure | CA3: Freight Cost | CB3: Currency | CC3: # Of Boxes | CD3: Commodity HTS-6 | CE3: Manufacturer Name | CF3: Manufacturer Address - Descriptor | CG3: Manufacturer Address 1 | CH3: Manufacturer Address 2 | CI3: Manufacturer Address 3 | CJ3: Manufacturer City | CK3: Manufacturer State | CL3: Manufacturer Country | CM3: Manufacturer Zip | CN3: Ref Order Type | CO3: Ref Order ID | CP3: Ref Order Line ID | CQ3: Ref Order Request ID | CR3: Ref Order Promise ID | CS3: Part Number (HCL) | CT3: Part Description (HCL) | CU3: Serial Number | CV3: Asset Tag Number
A4: ShipmentNumber001 | B4: Customer Code | C4: Customer Name | D4: Customer Address - Descriptor | E4: Customer Address 1 | F4: Customer Address 2 | G4: Customer Address 2 | H4: City | I4: NY | J4: US | K4: 12343 | L4: Supplier Code | M4: Supplier Name | N4: Supplier Address - Descriptor | O4: Supplier Address 1 | P4: Supplier Address 2 | Q4: Supplier Address 2 | R4: City | S4: NY | T4: US | U4: 12344 | V4: 2022-09-15T15:27:59+0000 | X4: 2022-09-14T00:00:00+0000 | Y4: 2022-09-25T00:00:00+0000 | Z4: 2022-09-24T00:00:00+0000 | AA4: Last Known Milestone | AB4: 2022-09-15T00:00:00+0000 | AC4: 2022-09-16T00:00:00+0000 | AD4: Carrier Name | AE4: OCEAN | AF4: Waybill Number | AG4: Shipment Delivery BOL Number | AH4: Packing Slip Number | AI4: Carrier Reference Number | AJ4: Shipper Reference Number | AK4: Site | AL4: Country Of Origin | AM4: 2 | AN4: Importer Of Record Number | AO4: Consignee Number | AP4: Place of Delivery | AQ4: Customer Site Code | AR4: Customer Site Name | AS4: Ship To Address - Descriptor | AT4: Ship To Address 1 | AU4: Ship To Address 2 | AV4: Ship To Address 3 | AW4: City | AX4: NY | AY4: US | AZ4: 12345 | BA4: Supplier Site | BB4: Ship From Address - Descriptor | BC4: Ship From Address 1 | BD4: Ship From Address 2 | BE4: Ship From Address 3 | BF4: City | BG4: NY | BH4: US | BI4: 12346 | BJ4: Bill To Code | BK4: Bill To Address - Descriptor | BL4: Bill To Address 1 | BM4: Bill To Address 2 | BN4: Bill To Address 3 | BO4: City | BP4: NY | BQ4: US | BR4: 12346 | BT4: 1 | BV4: InsertOrUpdate | BW4: Supplier Part Number 001 | BX4: Supplier Part 001 Description | BY4: 2 | BZ4: EA | CA4: Freight Cost | CB4: USD | CC4: 2 | CD4: 090962 | CF4: Manufacturer Address - Descriptor | CG4: Manufacturer Address 1 | CH4: Manufacturer Address 2 | CI4: Manufacturer Address 3 | CJ4: City | CK4: NY | CL4: US | CM4: 12346 | CN4: DiscreteOrder | CO4: PO Number 001 | CP4: 0010 | CQ4: 1 | CR4: 1 | CS4: HCL Part Number 001 | CT4: HCL Part 001 Description | CU4: Serial Number 1.1 | CV4: Asset Tag Number 1.1
A5: ShipmentNumber001 | B5: Customer Code | C5: Customer Name | D5: Customer Address - Descriptor | E5: Customer Address 1 | F5: Customer Address 2 | G5: Customer Address 2 | H5: City | I5: NY | J5: US | K5: 12343 | L5: Supplier Code | M5: Supplier Name | N5: Supplier Address - Descriptor | O5: Supplier Address 1 | P5: Supplier Address 2 | Q5: Supplier Address 2 | R5: City | S5: NY | T5: US | U5: 12344 | V5: 2022-09-15T15:27:59+0000 | X5: 2022-09-14T00:00:00+0000 | Y5: 2022-09-25T00:00:00+0000 | Z5: 2022-09-24T00:00:00+0000 | AA5: Last Known Milestone | AB5: 2022-09-15T00:00:00+0000 | AC5: 2022-09-16T00:00:00+0000 | AD5: Carrier Name | AE5: OCEAN | AF5: Waybill Number | AG5: Shipment Delivery BOL Number | AH5: Packing Slip Number | AI5: Carrier Reference Number | AJ5: Shipper Reference Number | AK5: Site | AL5: Country Of Origin | AM5: 2 | AN5: Importer Of Record Number | AO5: Consignee Number | AP5: Place of Delivery | AQ5: Customer Site Code | AR5: Customer Site Name | AS5: Ship To Address - Descriptor | AT5: Ship To Address 1 | AU5: Ship To Address 2 | AV5: Ship To Address 3 | AW5: City | AX5: NY | AY5: US | AZ5: 12345 | BA5: Supplier Site | BB5: Ship From Address - Descriptor | BC5: Ship From Address 1 | BD5: Ship From Address 2 | BE5: Ship From Address 3 | BF5: City | BG5: NY | BH5: US | BI5: 12346 | BJ5: Bill To Code | BK5: Bill To Address - Descriptor | BL5: Bill To Address 1 | BM5: Bill To Address 2 | BN5: Bill To Address 3 | BO5: City | BP5: NY | BQ5: US | BR5: 12346 | BT5: 1 | BV5: InsertOrUpdate | BW5: Supplier Part Number 001 | BX5: Supplier Part 001 Description | BY5: 2 | BZ5: EA | CA5: Freight Cost | CB5: USD | CC5: 2 | CD5: 090962 | CF5: Manufacturer Address - Descriptor | CG5: Manufacturer Address 1 | CH5: Manufacturer Address 2 | CI5: Manufacturer Address 3 | CJ5: City | CK5: NY | CL5: US | CM5: 12346 | CN5: DiscreteOrder | CO5: PO Number 001 | CP5: 0010 | CQ5: 1 | CR5: 1 | CS5: HCL Part Number 001 | CT5: HCL Part 001 Description | CU5: Serial Number 1.2 | CV5: Asset Tag Number 1.2
A6: ShipmentNumber001 | B6: Customer Code | C6: Customer Name | D6: Customer Address - Descriptor | E6: Customer Address 1 | F6: Customer Address 2 | G6: Customer Address 2 | H6: City | I6: NY | J6: US | K6: 12343 | L6: Supplier Code | M6: Supplier Name | N6: Supplier Address - Descriptor | O6: Supplier Address 1 | P6: Supplier Address 2 | Q6: Supplier Address 2 | R6: City | S6: NY | T6: US | U6: 12344 | V6: 2022-09-15T15:27:59+0000 | X6: 2022-09-14T00:00:00+0000 | Y6: 2022-09-25T00:00:00+0000 | Z6: 2022-09-24T00:00:00+0000 | AA6: Last Known Milestone | AB6: 2022-09-15T00:00:00+0000 | AC6: 2022-09-16T00:00:00+0000 | AD6: Carrier Name | AE6: OCEAN | AF6: Waybill Number | AG6: Shipment Delivery BOL Number | AH6: Packing Slip Number | AI6: Carrier Reference Number | AJ6: Shipper Reference Number | AK6: Site | AL6: Country Of Origin | AM6: 2 | AN6: Importer Of Record Number | AO6: Consignee Number | AP6: Place of Delivery | AQ6: Customer Site Code | AR6: Customer Site Name | AS6: Ship To Address - Descriptor | AT6: Ship To Address 1 | AU6: Ship To Address 2 | AV6: Ship To Address 3 | AW6: City | AX6: NY | AY6: US | AZ6: 12345 | BA6: Supplier Site | BB6: Ship From Address - Descriptor | BC6: Ship From Address 1 | BD6: Ship From Address 2 | BE6: Ship From Address 3 | BF6: City | BG6: NY | BH6: US | BI6: 12346 | BJ6: Bill To Code | BK6: Bill To Address - Descriptor | BL6: Bill To Address 1 | BM6: Bill To Address 2 | BN6: Bill To Address 3 | BO6: City | BP6: NY | BQ6: US | BR6: 12346 | BT6: 2 | BV6: InsertOrUpdate | BW6: Supplier Part Number 002 | BX6: Supplier Part 002 Description | BY6: 3 | BZ6: EA | CA6: Freight Cost | CB6: USD | CC6: 3 | CD6: 090962 | CF6: Manufacturer Address - Descriptor | CG6: Manufacturer Address 1 | CH6: Manufacturer Address 2 | CI6: Manufacturer Address 3 | CJ6: City | CK6: NY | CL6: US | CM6: 12346 | CN6: DiscreteOrder | CO6: PO Number 001 | CP6: 0020 | CQ6: 1 | CR6: 1 | CS6: HCL Part Number 002 | CT6: HCL Part 002 Description | CU6: Serial Number 2.1 | CV6: Asset Tag Number 2.1
A7: ShipmentNumber001 | B7: Customer Code | C7: Customer Name | D7: Customer Address - Descriptor | E7: Customer Address 1 | F7: Customer Address 2 | G7: Customer Address 2 | H7: City | I7: NY | J7: US | K7: 12343 | L7: Supplier Code | M7: Supplier Name | N7: Supplier Address - Descriptor | O7: Supplier Address 1 | P7: Supplier Address 2 | Q7: Supplier Address 2 | R7: City | S7: NY | T7: US | U7: 12344 | V7: 2022-09-15T15:27:59+0000 | X7: 2022-09-14T00:00:00+0000 | Y7: 2022-09-25T00:00:00+0000 | Z7: 2022-09-24T00:00:00+0000 | AA7: Last Known Milestone | AB7: 2022-09-15T00:00:00+0000 | AC7: 2022-09-16T00:00:00+0000 | AD7: Carrier Name | AE7: OCEAN | AF7: Waybill Number | AG7: Shipment Delivery BOL Number | AH7: Packing Slip Number | AI7: Carrier Reference Number | AJ7: Shipper Reference Number | AK7: Site | AL7: Country Of Origin | AM7: 2 | AN7: Importer Of Record Number | AO7: Consignee Number | AP7: Place of Delivery | AQ7: Customer Site Code | AR7: Customer Site Name | AS7: Ship To Address - Descriptor | AT7: Ship To Address 1 | AU7: Ship To Address 2 | AV7: Ship To Address 3 | AW7: City | AX7: NY | AY7: US | AZ7: 12345 | BA7: Supplier Site | BB7: Ship From Address - Descriptor | BC7: Ship From Address 1 | BD7: Ship From Address 2 | BE7: Ship From Address 3 | BF7: City | BG7: NY | BH7: US | BI7: 12346 | BJ7: Bill To Code | BK7: Bill To Address - Descriptor | BL7: Bill To Address 1 | BM7: Bill To Address 2 | BN7: Bill To Address 3 | BO7: City | BP7: NY | BQ7: US | BR7: 12346 | BT7: 2 | BV7: InsertOrUpdate | BW7: Supplier Part Number 002 | BX7: Supplier Part 002 Description | BY7: 3 | BZ7: EA | CA7: Freight Cost | CB7: USD | CC7: 3 | CD7: 090962 | CF7: Manufacturer Address - Descriptor | CG7: Manufacturer Address 1 | CH7: Manufacturer Address 2 | CI7: Manufacturer Address 3 | CJ7: City | CK7: NY | CL7: US | CM7: 12346 | CN7: DiscreteOrder | CO7: PO Number 001 | CP7: 0020 | CQ7: 1 | CR7: 1 | CS7: HCL Part Number 002 | CT7: HCL Part 002 Description | CU7: Serial Number 2.2 | CV7: Asset Tag Number 2.2
A8: ShipmentNumber001 | B8: Customer Code | C8: Customer Name | D8: Customer Address - Descriptor | E8: Customer Address 1 | F8: Customer Address 2 | G8: Customer Address 2 | H8: City | I8: NY | J8: US | K8: 12343 | L8: Supplier Code | M8: Supplier Name | N8: Supplier Address - Descriptor | O8: Supplier Address 1 | P8: Supplier Address 2 | Q8: Supplier Address 2 | R8: City | S8: NY | T8: US | U8: 12344 | V8: 2022-09-15T15:27:59+0000 | X8: 2022-09-14T00:00:00+0000 | Y8: 2022-09-25T00:00:00+0000 | Z8: 2022-09-24T00:00:00+0000 | AA8: Last Known Milestone | AB8: 2022-09-15T00:00:00+0000 | AC8: 2022-09-16T00:00:00+0000 | AD8: Carrier Name | AE8: OCEAN | AF8: Waybill Number | AG8: Shipment Delivery BOL Number | AH8: Packing Slip Number | AI8: Carrier Reference Number | AJ8: Shipper Reference Number | AK8: Site | AL8: Country Of Origin | AM8: 2 | AN8: Importer Of Record Number | AO8: Consignee Number | AP8: Place of Delivery | AQ8: Customer Site Code | AR8: Customer Site Name | AS8: Ship To Address - Descriptor | AT8: Ship To Address 1 | AU8: Ship To Address 2 | AV8: Ship To Address 3 | AW8: City | AX8: NY | AY8: US | AZ8: 12345 | BA8: Supplier Site | BB8: Ship From Address - Descriptor | BC8: Ship From Address 1 | BD8: Ship From Address 2 | BE8: Ship From Address 3 | BF8: City | BG8: NY | BH8: US | BI8: 12346 | BJ8: Bill To Code | BK8: Bill To Address - Descriptor | BL8: Bill To Address 1 | BM8: Bill To Address 2 | BN8: Bill To Address 3 | BO8: City | BP8: NY | BQ8: US | BR8: 12346 | BT8: 2 | BV8: InsertOrUpdate | BW8: Supplier Part Number 002 | BX8: Supplier Part 002 Description | BY8: 3 | BZ8: EA | CA8: Freight Cost | CB8: USD | CC8: 3 | CD8: 090962 | CF8: Manufacturer Address - Descriptor | CG8: Manufacturer Address 1 | CH8: Manufacturer Address 2 | CI8: Manufacturer Address 3 | CJ8: City | CK8: NY | CL8: US | CM8: 12346 | CN8: DiscreteOrder | CO8: PO Number 001 | CP8: 0020 | CQ8: 1 | CR8: 1 | CS8: HCL Part Number 002 | CT8: HCL Part 002 Description | CU8: Serial Number 3.2 | CV8: Asset Tag Number 3.2

Sheet Sample 856
A1: ISA*00* *00* *ZZ*Interchange Sen*ZZ*Interchange Rec*220915*1527*U*00401*000000001*0*P*~'
A2: GS*SH*Application Sen*Application Rec*20220915*152759*100000*X*004010'
A3: ST*856*0001'
A4: BSN*00*ShipmentNumber001*20220915*152759'
A5: HL*1**S'
A6: TD1*PKG*2'
A7: TD5*B*ZZ*Carrier Name*A***PL*Place of Delivery'
A8: REF*76*Last Known Milestone'
A9: REF*WY*Waybill Number'
A10: REF*BM*Shipment Delivery BOL Number'
A11: REF*PK*Packing Slip Number'
A12: REF*ZH*Carrier Reference Number'
... A85: IEA*1*000000001'

Sheet MtimShipmentLot
A1: Mapping Preconditions:
A3: Index | B3: Field Name | C3: Index | D3: Display Name | E3: Index | F3: Field Description | G3: Data Type | H3: Required | I3: Validation | J3: SSP Label Bundle | K3: Derived Formula | L3: FlexCDM Data | M3: Used | N3: DB Data Type
A4: 0 | B4: ShipmentId | C4: 0 | D4: Shipment ID | E4: 0 | F4: * Shipment Number * Unique by CustomerName and SupplierName. Can be the same value if either of these change * Change in value is unpermitted | G4: String(64) | H4: Yes | J4: ssp.res.shipment.id | L4: *,*.down | M4: Both | N4: VARCHAR(64)
A5: 1 | B5: CustomerName | C5: 1 | D5: Customer ID | E5: 1 | F5: * Customer ID for the Shipment * Should match the "ERP_Code" in the Referenced Order spec * Value is validated in the InsertOrUpdate upload | G5: String(64) | H5: Yes | I5: regex="${ssp.regex.validation.erp.customer.code}" | J5: ssp.res.erp.customer.code | K5: groovy= return (input[index(<%AsnLineItem.PdfString11%>)] == '$null') ? input[index(<%AsnHeader.CustomerName%>)] : input[index(<%AsnLineItem.PdfString11%>)] | L5: *,*.down | M5: Both | N5: VARCHAR(64)
A6: 2 | B6: CustomerDescription | C6: 2 | D6: Customer Description | E6: 2 | F6: * User-friendly description of CustomerName entry * Pass-through field in InsertOrUpdate * Preferably match the "ERP_Code_Description" in the Referenced Order spec, but need not match | G6: String(255) | H6: No | J6: ssp.res.erp.code.description | K6: groovy= return (input[index(<%AsnLineItem.PdfString11%>)] == '$null') ? input[index(<%AsnHeader.CustomerDescription%>)] : input[index(<%AsnLineItem.PdfString14%>)] | L6: *,*.down | M6: Both | N6: VARCHAR(255)
A7: 3 | B7: CustomerDUNS | C7: 3 | D7: Customer DUNS | E7: 3 | F7: * Customer DUNS number * Pass-through field in InsertOrUpdate * Preferably match the "DUNS" in the HUB spec, but need not match * Used for B2B Integration | G7: String(64) | H7: No | J7: ssp.res.customer.duns | L7: *,*.down | M7: Both | N7: VARCHAR(64)
A8: 4 | B8: CustomerDUNS4 | C8: 4 | D8: Customer DUNS+4 | E8: 4 | F8: * Customer DUNS+4 number * Pass-through field in InsertOrUpdate * Used for B2B Integration | G8: String(64) | H8: No | J8: ssp.res.customer.duns4 | L8: *,*.down | M8: Both | N8: VARCHAR(64)
A9: 5 | B9: CustomerAddressDescriptor | C9: 5 | D9: Customer Address - Descriptor | E9: 5 | F9: * Customer Address Field 1 * Preferably match "Cust/Supp_Address-Descriptor" in HUB spec, but need not match * In InsertOrUpdate persisted if presented, otherwise will use the previous value | G9: String(64) | H9: No | J9: ssp.res.customer.address.descriptor | L9: *,*.down | M9: Both | N9: VARCHAR(255)
A10: 6 | B10: CustomerAddress1 | C10: 6 | D10: Customer Address 1 | E10: 6 | F10: * Customer Address Field 2 * Preferably match "Cust/Supp_Address-Address1" in HUB spec but need not match * In InsertOrUpdate persisted if presented, otherwise will use the previous value | G10: String(256) | H10: No | J10: ssp.res.customer.address1 | L10: *,*.down | M10: Both | N10: VARCHAR(1024)
A11: 7 | B11: CustomerAddress2 | C11: 7 | D11: Customer Address 2 | E11: 7 | F11: * Customer Address Field 3 * Preferably match "Cust/Supp_Address-Address2" in HUB spec, but need not match * In InsertOrUpdate persisted if presented, otherwise will use the previous value | G11: String(256) | H11: No | J11: ssp.res.customer.address2 | L11: *,*.down | M11: Both | N11: VARCHAR(1024)
A12: 8 | B12: CustomerAddress3 | C12: 8 | D12: Customer Address 3 | E12: 8 | F12: * Customer Address Field 4 * Preferably match "Cust/Supp_Address-Address3" in HUB spec, but need not match * In InsertOrUpdate persisted if presented, otherwise will use the previous value | G12: String(256) | H12: No | J12: ssp.res.customer.address3 | L12: *,*.down | M12: Both | N12: VARCHAR(1024)
A13: 9 | B13: CustomerAddress4 | C13: 9 | D13: Customer Address 4 | E13: 9 | F13: * Customer Address Field 5 * Preferably match "Cust/Supp_Address-Address4" in HUB spec, but need not match * In InsertOrUpdate persisted if presented, otherwise will use the previous value | G13: String(256) | H13: No | J13: ssp.res.customer.address4 | L13: *,*.down | M13: Both | N13: VARCHAR(1024)
A14: 10 | B14: CustomerAddress5 | C14: 10 | D14: Customer Address 5 | E14: 10 | F14: * Customer Address Field 6 * Preferably match "Cust/Supp_Address-Address5" in HUB spec, but need not match * In InsertOrUpdate persisted if presented, otherwise will use the previous value | G14: String(256) | H14: No | J14: ssp.res.customer.address5 | L14: *,*.down | M14: Both | N14: VARCHAR(1024)
A15: 11 | B15: CustomerAddressCity | C15: 11 | D15: Customer City | E15: 11 | F15: * Customer Address Field 7 * Preferably match "Cust/Supp_Address-City" in HUB spec, but need not match * In InsertOrUpdate persisted if presented, otherwise will use the previous value | G15: String(64) | H15: No | J15: ssp.res.customer.address.city | L15: *,*.down | M15: Both | N15: VARCHAR(255)
A16: 12 | B16: CustomerAddressCounty | C16: 12 | D16: Customer County | E16: 12 | F16: * Customer Address Field 8 * Preferably match "Cust/Supp_Address-County" in HUB spec, but need not match * In InsertOrUpdate persisted if presented, otherwise will use the previous value | G16: String(64) | H16: No | J16: ssp.res.customer.address.county | L16: *,*.down | M16: Both | N16: VARCHAR(255)
A17: 13 | B17: CustomerAddressState | C17: 13 | D17: Customer State | E17: 13 | F17: * Customer Address Field 9 * Preferably match "Cust/Supp_Address-State" in HUB spec, but need not match * In InsertOrUpdate persisted if presented, otherwise will use the previous value | G17: String(64) | H17: No | J17: ssp.res.customer.address.state | L17: *,*.down | M17: Both | N17: VARCHAR(255)
A18: 14 | B18: CustomerAddressCountry | C18: 14 | D18: Customer Country | E18: 14 | F18: * Customer Address Field 10 * Preferably match "Cust/Supp_Address-Country" in HUB spec, but need not match * In InsertOrUpdate persisted if presented, otherwise will use the previous value | G18: String(64) | H18: No | J18: ssp.res.customer.address.country | L18: *,*.down | M18: Both | N18: VARCHAR(255)
A19: 15 | B19: CustomerAddressZip | C19: 15 | D19: Customer Zip | E19: 15 | F19: * Customer Address Field 11 * Preferably match "Cust/Supp_Address-Zip" in HUB spec, but need not match * In InsertOrUpdate persisted if presented, otherwise will use the previous value | G19: String(64) | H19: No | J19: ssp.res.customer.address.zip.code | L19: *,*.down | M19: Both | N19: VARCHAR(255)
A20: 16 | B20: SupplierName | C20: 16 | D20: Supplier ID | E20: 16 | F20: * Supplier ID for the Shipment * Should match the "ERP_Code"_"ERP_Supplier_Code" where "ERP_Code" and "ERP_Supplier_Code" are in the SUPPLIER spec when multiple "ERP_Code" are implemented for the project * Should match the "ERP_Supplier_Code" in the SUPPLIER spec when a single "ERP_Code" is implemented for the project * Value is validated in the InsertOrUpdate upload | G20: String(64) | H20: Yes | I20: regex="${ssp.regex.validation.erp.supplier.code}" | J20: ssp.res.erp.supplier.code | L20: *,*.down | M20: Both | N20: VARCHAR(64)
A21: 17 | B21: SupplierDescription | C21: 17 | D21: Supplier Description | E21: 17 | F21: * User-friendly description of SupplierName entry * Pass-through field in InsertOrUpdate * Preferably match the "ERP_Supplier_Description" in the SUPPLIER spec, but need not match | G21: String(255) | H21: No | J21: ssp.res.erp.supplier.description | L21: *,*.down | M21: Both | N21: VARCHAR(255)
A22: 18 | B22: SupplierDUNS | C22: 18 | D22: Supplier DUNS | E22: 18 | F22: * Supplier DUNS number * Pass-through field in InsertOrUpdate * Preferably match the "DUNS" in the SUPPLIER spec, but need not match * Used for B2B Integration | G22: String(64) | H22: No | J22: ssp.res.supplier.duns | L22: *,*.down | M22: Both | N22: VARCHAR(64)
A23: 19 | B23: SupplierDUNS4 | C23: 19 | D23: Supplier DUNS+4 | E23: 19 | F23: * Supplier DUNS+4 number * Pass-through field in InsertOrUpdate * Used for B2B Integration | G23: String(64) | H23: No | J23: ssp.res.supplier.duns4 | L23: *,*.down | M23: Both | N23: VARCHAR(64)
A24: 20 | B24: SupplierAddressDescriptor | C24: 20 | D24: Supplier Address - Descriptor | E24: 20 | F24: * Supplier Address Field 1 * Preferably match "Supplier_Address-Descriptor" in SUPPLIER spec, but need not match * In InsertOrUpdate persisted if presented, otherwise will use the previous value | G24: String(64) | H24: No | J24: ssp.res.supplier.address.descriptor | L24: *,*.down | M24: Both | N24: VARCHAR(255)
A25: 21 | B25: SupplierAddress1 | C25: 21 | D25: Supplier Address 1 | E25: 21 | F25: * Supplier Address Field 2 * Preferably match "Supplier_Address-Address1" in SUPPLIER spec, but need not match * In InsertOrUpdate persisted if presented, otherwise will use the previous value | G25: String(256) | H25: No | J25: ssp.res.supplier.address1 | L25: *,*.down | M25: Both | N25: VARCHAR(1024)
A26: 22 | B26: SupplierAddress2 | C26: 22 | D26: Supplier Address 2 | E26: 22 | F26: * Supplier Address Field 3 * Preferably match "Supplier_Address-Address2" in SUPPLIER spec, but need not match * In InsertOrUpdate persisted if presented, otherwise will use the previous value | G26: String(256) | H26: No | J26: ssp.res.supplier.address2 | L26: *,*.down | M26: Both | N26: VARCHAR(1024)
A27: 23 | B27: SupplierAddress3 | C27: 23 | D27: Supplier Address 3 | E27: 23 | F27: * Supplier Address Field 4 * Preferably match "Supplier_Address-Address3" in SUPPLIER spec, but need not match * In InsertOrUpdate persisted if presented, otherwise will use the previous value | G27: String(256) | H27: No | J27: ssp.res.supplier.address3 | L27: *,*.down | M27: Both | N27: VARCHAR(1024)
A28: 24 | B28: SupplierAddress4 | C28: 24 | D28: Supplier Address 4 | E28: 24 | F28: * Supplier Address Field 5 * Preferably match "Supplier_Address-Address4" in SUPPLIER spec, but need not match * In InsertOrUpdate persisted if presented, otherwise will use the previous value | G28: String(256) | H28: No | J28: ssp.res.supplier.address4 | L28: *,*.down | M28: Both | N28: VARCHAR(1024)
A29: 25 | B29: SupplierAddress5 | C29: 25 | D29: Supplier Address 5 | E29: 25 | F29: * Supplier Address Field 6 * Preferably match "Supplier_Address-Address5" in SUPPLIER spec but need not match * In InsertOrUpdate persisted if presented, otherwise will use the previous value | G29: String(256) | H29: No | J29: ssp.res.supplier.address5 | L29: *,*.down | M29: Both | N29: VARCHAR(1024)
A30: 26 | B30: SupplierAddressCity | C30: 26 | D30: Supplier City | E30: 26 | F30: * Supplier Address Field 7 * Preferably match "Supplier_Address-City" in SUPPLIER spec, but need not match * In InsertOrUpdate persisted if presented, otherwise will use the previous value | G30: String(64) | H30: No | J30: ssp.res.supplier.address.city | L30: *,*.down | M30: Both | N30: VARCHAR(255)
A31: 27 | B31: SupplierAddressCounty | C31: 27 | D31: Supplier County | E31: 27 | F31: * Supplier Address Field 8 * Preferably match "Supplier_Address-County" in SUPPLIER spec, but need not match * In InsertOrUpdate persisted if presented, otherwise will use the previous value | G31: String(64) | H31: No | J31: ssp.res.supplier.address.county | L31: *,*.down | M31: Both | N31: VARCHAR(255)
A32: 28 | B32: SupplierAddressState | C32: 28 | D32: Supplier State | E32: 28 | F32: * Supplier Address Field 9 * Preferably match "Supplier_Address-State" in SUPPLIER spec, but need not match * In InsertOrUpdate persisted if presented, otherwise will use the previous value | G32: String(64) | H32: No | J32: ssp.res.supplier.address.state | L32: *,*.down | M32: Both | N32: VARCHAR(255)
... A36: 32 | B36: ShipmentCreatorCode | C36: 32 | D36: Shipment Creator Code | E36: 32 | F36: * ERP Shipment Creator Code for the Shipment * In InsertOrUpdate value persisted if not empty * Searchable field in the Web UI by default * Can be used to constain permissiblity for roles | G36: String(64) | H36: No | J36: ssp.res.shipment.creator.code | L36: *,*.down | M36: Both | N36: VARCHAR(64)
A37: 33 | B37: ShipmentStatus | C37: 33 | D37: Shipment Status | E37: 33 | F37: * Aggregate status based on underlying Shipment line status * SCPM server computed * Download-only field, to be presented as empty in all uploads. If presented as non-empty in upload, then an empty value is sent to the SCPM server and computed in SCPM server | G37: String(64) | H37: No | J37: ssp.res.shipment.status | K37: <%AsnHeader.AsnState%> | L37: *,*.down | N37: VARCHAR(64)
A38: =A37+1 -> 34 | B38: ShipmentDate | C38: =C37+1 -> 34 | D38: Shipment Date | E38: =E37+1 -> 34 | F38: * The ERP Shipped Date for the Referenced Order. * The values allowed must be on or after the Current Day of the week (past requests are not allowed) * Update only allowed in InsertOrUpdate | G38: DATE | H38: Yes | J38: ssp.res.shipment.date | L38: *,*.down | M38: Both | N38: DATE
A39: =A38+1 -> 35 | B39: PlannedDeliveryDate | C39: =C38+1 -> 35 | D39: Planned Delivery Date | E39: =E38+1 -> 35 | F39: * The ERP Planned Delivery Date for the Referenced Order. * The values allowed must be on or after the Current Day of the week (past requests are not allowed) * Update only allowed in InsertOrUpdate | G39: DATE | H39: Yes | J39: ssp.res.planned.delivery.date | L39: *,*.down | M39: Both | N39: DATE
A40: =A39+1 -> 36 | B40: ETAAtFinalSite | C40: =C39+1 -> 36 | D40: Final Site ETA | E40: =E39+1 -> 36 | F40: * The Carrier updates Estimated Time of Arrival of the Shipment. * The values allowed must be on or after the Current Day of the week (past requests are not allowed) * Update only allowed in InsertOrUpdate | G40: DATE | H40: No | J40: ssp.res.eta.at.final.site | L40: *,*.down | M40: Both | N40: DATE
A41: =A40+1 -> 37 | B41: LastKnownMilestone | C41: =C40+1 -> 37 | D41: Last Known Milestone | E41: =E40+1 -> 37 | F41: * The Carrier updates Last Known Milestone of the Shipment. * The values allowed must be on or after the Current Day of the week (past requests are not allowed) * Update only allowed in InsertOrUpdate | G41: String(255) | H41: No | J41: ssp.res.last.known.milestone | L41: *,*.down | M41: Both | N41: VARCHAR(255)
A42: =A41+1 -> 38 | B42: ArrivalAtLastKnownMilestone | C42: =C41+1 -> 38 | D42: Last Known Milestone Arrival | E42: =E41+1 -> 38 | F42: * The Carrier updates Arrival Last Known Milestone of the Shipment. * The values allowed must be on or after the Current Day of the week (past requests are not allowed) * Update only allowed in InsertOrUpdate | G42: DATE | H42: No | J42: ssp.res.arrival.at.last.known.milestone | L42: *,*.down | M42: Both | N42: DATE
A43: =A42+1 -> 39 | B43: DepartureFromLastKnownMilestone | C43: =C42+1 -> 39 | D43: Last Known Milestone Departure | E43: =E42+1 -> 39 | F43: * The Carrier updates Departure Last Known Milestone of the Shipment. * The values allowed must be on or after the Current Day of the week (past requests are not allowed) * Update only allowed in InsertOrUpdate | G43: DATE | H43: No | J43: ssp.res.departure.from.last.known.milestone | L43: *,*.down | M43: Both | N43: DATE
A44: =A43+1 -> 40 | B44: CarrierName | C44: =C43+1 -> 40 | D44: Carrier | E44: =E43+1 -> 40 | F44: * The ERP requested Carrier for the Shipment * Pass-through field in InsertOrUpdate | G44: String(64) | H44: No | J44: ssp.res.carrier | L44: *,*.down | M44: Both | N44: VARCHAR(64)
A45: =A44+1 -> 41 | B45: ShipmentMode | C45: =C44+1 -> 41 | D45: Shipment Mode | E45: =E44+1 -> 41 | F45: * The ERP specified mode that shipment is transported. * Pass-through field in InsertOrUpdate. | G45: String(64) | H45: No | J45: ssp.res.shipment.mode | L45: *,*.down | M45: Both | N45: VARCHAR(64)
A46: =A45+1 -> 42 | B46: WaybillNumber | C46: =C45+1 -> 42 | D46: Waybill # | E46: =E45+1 -> 42 | F46: * The ERP Shipment tracking number. * Pass-through field in InsertOrUpdate. | G46: String(64) | H46: No | J46: ssp.res.way.bill.number | L46: *,*.down | M46: Both | N46: VARCHAR(64)
A47: =A46+1 -> 43 | B47: ShipmentDeliveryBOLNumber | C47: =C46+1 -> 43 | D47: Shipment Delivery BOL # | E47: =E46+1 -> 43 | F47: * The ERP Bill of Lading Number that referenced binding document between a Supplier and Carrier. * The document details all the information needed to process a freight shipment. * Pass-through field in InsertOrUpdate. | G47: String(64) | H47: No | J47: ssp.res.shipment.delivery.bol.number | L47: *,*.down | M47: Both | N47: VARCHAR(64)
A48: =A47+1 -> 44 | B48: PackingSlipNumber | C48: =C47+1 -> 44 | D48: Packing Slip # | E48: =E47+1 -> 44 | F48: * The number referenced the packing slip on the Shipment. * Shipping document that serves as a record of the content in the shipment. * Pass-through field in InsertOrUpdate. | G48: String(64) | H48: No | J48: ssp.res.packing.slip.number.header | L48: *,*.down | M48: Both | N48: VARCHAR(64)
A49: =A48+1 -> 45 | B49: CarrierReferenceNumber | C49: =C48+1 -> 45 | D49: Carrier Reference # | E49: =E48+1 -> 45 | F49: * The ERP Carrier Reference Number is used by Carriers as a reference for freight movement. * Pass-through field in InsertOrUpdate. | G49: String(64) | H49: No | J49: ssp.res.carrier.reference.number | L49: *,*.down | M49: Both | N49: VARCHAR(64)
A50: =A49+1 -> 46 | B50: ShipperReferenceNumber | C50: =C49+1 -> 46 | D50: Shipper Reference # | E50: =E49+1 -> 46 | F50: * The ERP Shipment Reference Number is an unique identifier of the Shipment. * Usually provided/updated by the Carrier. * Pass-through field in InsertOrUpdate. | G50: String(64) | H50: No | J50: ssp.res.shipper.reference.number | L50: *,*.down | M50: Both | N50: VARCHAR(64)
A51: =A50+1 -> 47 | B51: ShipToLocationType | C51: =C50+1 -> 47 | D51: Ship To Type (Site/Hub) | E51: =E50+1 -> 47 | F51: * The system level indicator of shipped to location type. * Utilized by SCPM to determine how Shipment is aggregated or computed. * Value is validated in the InsertOrUpdate upload. | G51: String(64) | H51: Yes | I51: enum=(Hub|Site) | J51: ssp.res.ship.to.location.type | L51: *,*.down | M51: Both | N51: VARCHAR(64)
A52: =A51+1 -> 48 | B52: CountryOfOrigin | C52: =C51+1 -> 48 | D52: Country Of Origin | E52: =E51+1 -> 48 | F52: * The ERP Country of Origin is the country where goods or products comes from. * Usually provided/updated by the Carrier. * Pass-through field in InsertOrUpdate. | G52: String(64) | H52: No | J52: ssp.res.country.of.origin | L52: *,*.down | M52: Both | N52: VARCHAR(64)
A53: =A52+1 -> 49 | B53: NumberOfPackages | C53: =C52+1 -> 49 | D53: Number Of Packages | E53: =E52+1 -> 49 | F53: * Amount of shipped goods in packages unit * Pass-through field in InsertOrUpdate. | G53: Integer(10) | H53: No | J53: ssp.res.number.of.packages | L53: *,*.down | M53: Both | N53: NUMBER(10)
A54: =A53+1 -> 50 | B54: LicensePlateNumber | C54: =C53+1 -> 50 | D54: License Plate | E54: =E53+1 -> 50 | F54: * Unique identifier for vehicle transporting the Shipment. * Pass-through field in InsertOrUpdate. | G54: String(255) | H54: No | J54: ssp.res.license.plate.number | L54: *,*.down | M54: Both | N54: VARCHAR(255)
A55: =A54+1 -> 51 | B55: ImporterOfRecordNumber | C55: =C54+1 -> 51 | D55: Importer Of # | E55: =E54+1 -> 51 | F55: * Customs term for the entity responsible for * (1) ensuring the imported goods comply with local laws and regulations, * (2) filing a completed duty entry and associated documents and (3) paying the assessed import duties and other taxes on those goods." * Pass-through field in InsertOrUpdate | G55: String(64) | H55: No | J55: ssp.res.importer.of.record.number | L55: *,*.down | M55: Both | N55: VARCHAR(64)
A56: =A55+1 -> 52 | B56: ConsigneeNumber | C56: =C55+1 -> 52 | D56: Consignee # | E56: =E55+1 -> 52 | F56: * The ERP Consignee Number that identify entity finanacially responsible for the receipt of the Shipment. * Pass-through field in InsertOrUpdate. | G56: String(64) | H56: No | J56: ssp.res.consignee.number | L56: *,*.down | M56: Both | N56: VARCHAR(64)
A57: =A56+1 -> 53 | B57: ForeignPortOfUnlading | C57: =C56+1 -> 53 | D57: Foreign Port Of Unlading | E57: =E56+1 -> 53 | F57: * The port in a foreign country where the goods are removed from the exporting carrier. * Pass-through field in InsertOrUpdate. | G57: String(64) | H57: No | J57: ssp.res.foreign.port.of.unlading | L57: *,*.down | M57: Both | N57: VARCHAR(64)
A58: =A57+1 -> 54 | B58: PlaceOfDelivery | C58: =C57+1 -> 54 | D58: Place Of Delivery | E58: =E57+1 -> 54 | F58: * The location, can be different from Ship To Site, that is agreed amoung Supplier, Buyer, and Carrier. * Goods are handed over from Supplier to the Carrier and also where risk passes from Supplier to the Buyer. * Pass-through field in InsertOrUpdate | G58: String(64) | H58: No | J58: ssp.res.place.of.delivery | L58: *,*.down | M58: Both | N58: VARCHAR(64)
A59: =A58+1 -> 55 | B59: ShipToSite | C59: =C58+1 -> 55 | D59: Ship To Site | E59: =E58+1 -> 55 | F59: * The Ship To Site on the Shipment Schedule * Should match the "ERP_Site" in the HUB spec used to define the ship to sites * Key field established and validated in Shipment Schedule creation by InsertOrUpdate * Change in value is unpermitted | G59: String(64) | H59: Yes | I59: regex="${ssp.regex.validation.erp.ship.to.site}" | J59: ssp.res.ship.to.site | L59: *,*.down | M59: Both | N59: VARCHAR(64)
A60: =A59+1 -> 56 | B60: ShipToPartyName | C60: =C59+1 -> 56 | D60: Ship-to-Party Name | E60: =E59+1 -> 56 | F60: * The Remote Customer for the CustomerSite if different from CustomerName * The ShipToPartyName must correspond to a valid "ERP_Code" in the HUB spec | G60: String(64) | H60: No | J60: ssp.res.ship.to.party.name | L60: *,*.down | M60: Both | N60: VARCHAR(64)
A61: =A60+1 -> 57 | B61: ShipToPartyDUNS | C61: =C60+1 -> 57 | D61: Ship-to-Party DUNS | E61: =E60+1 -> 57 | F61: * Ship To Party DUNS number * Pass-through field in InsertOrUpdate * Preferably match the "DUNS" in the HUB spec, but need not match * Used for B2B Integration | G61: String(64) | H61: No | J61: ssp.res.ship.to.party.duns | L61: *,*.down | M61: Both | N61: VARCHAR(64)
A62: =A61+1 -> 58 | B62: ShipToAddressDescriptor | C62: =C61+1 -> 58 | D62: Ship To Address - Descriptor | E62: =E61+1 -> 58 | F62: * Ship to Address Field 1 * Preferably match "Cust/Supp_Address-Descriptor" in HUB spec, but need not match * In InsertOrUpdate persisted if presented, otherwise will use the previous value | G62: String(64) | H62: No | J62: ssp.res.ship.to.address.descriptor | L62: *,*.down | M62: Both | N62: VARCHAR(255)
A63: =A62+1 -> 59 | B63: ShipToAddress1 | C63: =C62+1 -> 59 | D63: Ship To Address 1 | E63: =E62+1 -> 59 | F63: * Ship to Address Field 2 * Preferably match "Cust/Supp_Address-Address1" in HUB spec but need not match * In InsertOrUpdate persisted if presented, otherwise will use the previous value | G63: String(256) | H63: No | J63: ssp.res.ship.to.address1 | L63: *,*.down | M63: Both | N63: VARCHAR(1024)
A64: =A63+1 -> 60 | B64: ShipToAddress2 | C64: =C63+1 -> 60 | D64: Ship To Address 2 | E64: =E63+1 -> 60 | F64: * Ship to Address Field 3 * Preferably match "Cust/Supp_Address-Address2" in HUB spec, but need not match * In InsertOrUpdate persisted if presented, otherwise will use the previous value | G64: String(256) | H64: No | J64: ssp.res.ship.to.address2 | L64: *,*.down | M64: Both | N64: VARCHAR(1024)
A65: =A64+1 -> 61 | B65: ShipToAddress3 | C65: =C64+1 -> 61 | D65: Ship To Address 3 | E65: =E64+1 -> 61 | F65: * Ship to Address Field 4 * Preferably match "Cust/Supp_Address-Address3" in HUB spec, but need not match * In InsertOrUpdate persisted if presented, otherwise will use the previous value | G65: String(256) | H65: No | J65: ssp.res.ship.to.address3 | L65: *,*.down | M65: Both | N65: VARCHAR(1024)
A66: =A65+1 -> 62 | B66: ShipToAddress4 | C66: =C65+1 -> 62 | D66: Ship To Address 4 | E66: =E65+1 -> 62 | F66: * Ship to Address Field 5 * Preferably match "Cust/Supp_Address-Address4" in HUB spec, but need not match * In InsertOrUpdate persisted if presented, otherwise will use the previous value | G66: String(256) | H66: No | J66: ssp.res.ship.to.address4 | L66: *,*.down | M66: Both | N66: VARCHAR(1024)
A67: =A66+1 -> 63 | B67: ShipToAddress5 | C67: =C66+1 -> 63 | D67: Ship To Address 5 | E67: =E66+1 -> 63 | F67: * Ship to Address Field 6 * Preferably match "Cust/Supp_Address-Address5" in HUB spec, but need not match * In InsertOrUpdate persisted if presented, otherwise will use the previous value | G67: String(256) | H67: No | J67: ssp.res.ship.to.address5 | L67: *,*.down | M67: Both | N67: VARCHAR(1024)
A68: =A67+1 -> 64 | B68: ShipToAddressCity | C68: =C67+1 -> 64 | D68: Ship To City | E68: =E67+1 -> 64 | F68: * Ship to Address Field 7 * Preferably match "Cust/Supp_Address-City" in HUB spec, but need not match * In InsertOrUpdate persisted if presented, otherwise will use the previous value | G68: String(64) | H68: No | J68: ssp.res.ship.to.address.city | L68: *,*.down | M68: Both | N68: VARCHAR(255)
A69: =A68+1 -> 65 | B69: ShipToAddressCounty | C69: =C68+1 -> 65 | D69: Ship To County | E69: =E68+1 -> 65 | F69: * Ship to Address Field 8 * Preferably match "Cust/Supp_Address-County" in HUB spec, but need not match * In InsertOrUpdate persisted if presented, otherwise will use the previous value | G69: String(64) | H69: No | J69: ssp.res.ship.to.address.county | L69: *,*.down | M69: Both | N69: VARCHAR(255)
A70: =A69+1 -> 66 | B70: ShipToAddressState | C70: =C69+1 -> 66 | D70: Ship To State | E70: =E69+1 -> 66 | F70: * Ship to Address Field 9 * Preferably match "Cust/Supp_Address-State" in HUB spec, but need not match * In InsertOrUpdate persisted if presented, otherwise will use the previous value | G70: String(64) | H70: No | J70: ssp.res.ship.to.address.state | L70: *,*.down | M70: Both | N70: VARCHAR(255)
A71: =A70+1 -> 67 | B71: ShipToAddressCountry | C71: =C70+1 -> 67 | D71: Ship To Country | E71: =E70+1 -> 67 | F71: * Ship to Address Field 10 * Preferably match "Cust/Supp_Address-Country" in HUB spec, but need not match * In InsertOrUpdate persisted if presented, otherwise will use the previous value | G71: String(64) | H71: No | J71: ssp.res.ship.to.address.country | L71: *,*.down | M71: Both | N71: VARCHAR(255)
... A134: =A133+1 -> 130 | B134: ShipmentLineItemId | C134: =C133+1 -> 130 | D134: Shipment Line ID | E134: =E133+1 -> 130 | F134: * Shipment Line Item Id * Key integer field established in Shipment Line creation by InsertOrUpdate * Change in value is unpermitted | G134: String(64) | H134: Yes | J134: ssp.res.shipment.line.item.id | L134: *,*.down | M134: Both | N134: VARCHAR(64)
A135: 131 | B135: ShipmentLineStatus | C135: 131 | D135: Shipment Line Status | E135: 131 | F135: * Status based on underlying Shipment Line actions and state change * SCPM server computed. If presented as non-empty in upload then an empty value is sent to the SCPM server and computed in SCPM server. * Download-only field, to be presented as empty in all uploads. | G135: String(64) | H135: No | J135: ssp.res.shipment.line.status | K135: <%AsnLineItem.LineItemState%> | L135: *,*.down | N135: VARCHAR(64)
A136: =A135+1 -> 132 | B136: Action | C136: =C135+1 -> 132 | D136: Action | E136: =E135+1 -> 132 | F136: * The Action to be performed from the inbound data for each Shipment Line sent independently to the SCPM server in the upload * Strictly restricts the values to be one of the following: InsertOrUpdate,SuppUpdate,CarrierUpdate,Deliver,Cancel where InsertOrUpdate is the main customer B2B Action * In the downloads for this mapping spec an empty value is returned * The field only appears in the audit trail in the Web UI | G136: String(64) | H136: Yes | I136: enum=(InsertOrUpdate|SuppUpdate|CarrierUpdate|Deliver|Cancel) | J136: ssp.res.shipment.action | K136: hard code "$null" | L136: *,*.down | M136: Both | N136: VARCHAR(64)
A137: =A136+1 -> 133 | B137: CustomerItemName | C137: =C136+1 -> 133 | D137: Customer Item ID | E137: =E136+1 -> 133 | F137: * The Customer Item for the Referenced Order Line Item * Should match the "ERP_Customer_Item" in the PURCHASED ITEMS spec * Key field established and validated in Purchase Order Line creation by InsertOrUpdate * Change in value is unpermitted | G137: String(64) | H137: Yes | I137: regex="${ssp.regex.validation.erp.customer.item}" | J137: ssp.res.erp.customer.item | K137: groovy= return (input[index(<%AsnLineItem.PdfString12%>)] == '$null') ? input[index(<%AsnLineItem.CustomerItemName%>)] : input[index(<%AsnLineItem.PdfString12%>)] | L137: *,*.down | M137: Both | N137: VARCHAR(64)
A138: =A137+1 -> 134 | B138: CustomerItemDescription | C138: =C137+1 -> 134 | D138: Customer Item Description | E138: =E137+1 -> 134 | F138: * User-friendly description of CustomerItemName entry * Pass-through field in InsertOrUpdate * Preferably match the "ERP_Customer_Item_Description" in the PURCHASED ITEMS spec but need not match | G138: String(255) | H138: No | J138: ssp.res.erp.customer.item.description | K138: groovy= return (input[index(<%AsnLineItem.PdfString13%>)] == '$null') ? input[index(<%AsnLineItem.CustomerItemDesc%>)] : input[index(<%AsnLineItem.PdfString13%>)] | L138: *,*.down | M138: Both | N138: VARCHAR(255)
A139: =A138+1 -> 135 | B139: SupplierItemName | C139: =C138+1 -> 135 | D139: Supplier Item ID | E139: =E138+1 -> 135 | F139: * The Supplier Item for the Referenced Order Line Item * Pass-through field in InsertOrUpdate * Preferably match the "ERP_Supplier_Item" in the PURCHASED ITEMS spec * Not a key field established, but validated in Purchase Order Line creation by InsertOrUpdate * Change in value is permitted * If sent empty then the Supplier Item established in "ERP_Supplier_Item" is used | G139: String(64) | H139: No | I139: regex="${ssp.regex.validation.erp.supplier.item}" | J139: ssp.res.erp.supplier.item | L139: *,*.down | M139: Both | N139: VARCHAR(64)
A140: =A139+1 -> 136 | B140: SupplierItemDescription | C140: =C139+1 -> 136 | D140: Supplier Item Description | E140: =E139+1 -> 136 | F140: * User-friendly description of SupplierItemName entry * Pass-through field in InsertOrUpdate * Preferably match the "ERP_Supplier_Item_Description" in the PURCHASED ITEMS spec but need not match | G140: String(255) | H140: No | J140: ssp.res.erp.supplier.item.description | L140: *,*.down | M140: Both | N140: VARCHAR(255)
A141: =A140+1 -> 137 | B141: BuyerCode | C141: =C140+1 -> 137 | D141: Buyer Code | E141: =E140+1 -> 137 | F141: * ERP Buyer Code for the Referenced Order * In InsertOrUpdate value persisted if not empty * Searchable field in the Web UI by default * Can be used to constain permissiblity for roles | G141: String(64) | H141: No | J141: ssp.res.buyer.code | L141: *,*.down | M141: Both | N141: VARCHAR(64)
A142: =A141+1 -> 138 | B142: ShippedQuantity | C142: =C141+1 -> 138 | D142: Shipped Quantity | E142: =E141+1 -> 138 | F142: * The ERP Shipped Quantity for the Referenced Order * The values allowed must be > 0 * Update only allowed in InsertOrUpdate | G142: Float(126) | H142: Yes | J142: ssp.res.shipped.quantity | L142: *,*.down | M142: Both | N142: Float(126)
A143: =A142+1 -> 139 | B143: UnitOfMeasure | C143: =C142+1 -> 139 | D143: Unit Of Measure | E143: =E142+1 -> 139 | F143: * The Unit of Measure for the price basis based on UnitPrice for the Shipment Line Item * Pass-through field in InsertOrUpdate * Shown in the Order detail page in SCPM | G143: String(64) | H143: No | J143: ssp.res.unit.of.measure | L143: *,*.down | M143: Both | N143: VARCHAR(64)
A144: =A143+1 -> 140 | B144: FreightCost | C144: =C143+1 -> 140 | D144: Freight Cost | E144: =E143+1 -> 140 | F144: * Freight cost is the the price incurred to ship your goods. * Pass-through field in InsertOrUpdate. | G144: Float(126) | H144: No | J144: ssp.res.freight.cost | L144: *,*.down | M144: Both | N144: Float(126)
A145: =A144+1 -> 141 | B145: Currency | C145: =C144+1 -> 141 | D145: Currency | E145: =E144+1 -> 141 | F145: * The item Currency stored at the Referenced Order Schedule level * Logically same as the steps in UnitPrice search | G145: String(64) | H145: No | J145: ssp.res.currency | L145: *,*.down | M145: Both | N145: VARCHAR(64)
A146: =A145+1 -> 142 | B146: PackingSlipNumberLine | C146: =C145+1 -> 142 | D146: Packing Slip # (Line) | E146: =E145+1 -> 142 | F146: * The number referenced the packing slip on the Shipment Line. * Shipping document that serves as a record of the content in the shipment. * Pass-through field in InsertOrUpdate. | G146: String(64) | H146: No | J146: ssp.res.packing.slip.number.line | L146: *,*.down | M146: Both | N146: VARCHAR(64)
A147: =A146+1 -> 143 | B147: LineNotesToCustomer | C147: =C146+1 -> 143 | D147: Notes To Customer | E147: =E146+1 -> 143 | F147: * Supplier notes to Customer for the Referenced Order Line Item * Pass-through field in supplier actions * Shown in the Web UI | G147: String(255) | H147: No | J147: ssp.res.lines.notes.to.customer | L147: *,*.down | M147: Both | N147: VARCHAR(255)
A148: =A147+1 -> 144 | B148: NumberOfBoxes | C148: =C147+1 -> 144 | D148: # Of Boxes | E148: =E147+1 -> 144 | F148: * Amount of shipped goods in boxes unit * Pass-through field in InsertOrUpdate. | G148: Integer(10) | H148: No | J148: ssp.res.number.of.boxes | L148: *,*.down | M148: Both | N148: NUMBER(10)
A149: =A148+1 -> 145 | B149: Weight | C149: =C148+1 -> 145 | D149: Weight | E149: =E148+1 -> 145 | F149: * Weight of shipped goods. * Pass-through field in InsertOrUpdate. | G149: Float(126) | H149: No | J149: ssp.res.weight | L149: *,*.down | M149: Both | N149: Float(126)
A150: =A149+1 -> 146 | B150: CommodityHTS-6 | C150: =C149+1 -> 146 | D150: Commodity HTS-6 | E150: =E149+1 -> 146 | F150: * The Harmonized Tariff Schedule commodity code is a 10-digit field that is specific to the United States. * Commodity duties are assessed based on this classification. * Pass-through field in InsertOrUpdate. | G150: String(64) | H150: No | J150: ssp.res.commodity.hts6 | L150: *,*.down | M150: Both | N150: VARCHAR(64)
A151: =A150+1 -> 147 | B151: ManufacturerName | C151: =C150+1 -> 147 | D151: Manufacturer Name | E151: =E150+1 -> 147 | F151: * The entity name responsible for manufacturing goods in the Shipment. * Pass-through field in InsertOrUpdate | G151: String(64) | H151: No | J151: ssp.res.manufacturer.name | L151: *,*.down | M151: Both | N151: VARCHAR(64)
... A191: =A190+1 -> 187 | B191: RefdOrderSupplier | C191: =C190+1 -> 187 | D191: Ref Supplier ID | E191: =E190+1 -> 187 | F191: * Referenced parent Order Supplier Name | G191: String(64) | H191: No | J191: ssp.res.refd.order.supplier | L191: *,*.down | M191: Both | N191: VARCHAR(64)
A192: =A191+1 -> 188 | B192: RefdOrderType | C192: =C191+1 -> 188 | D192: Ref Order Type | E192: =E191+1 -> 188 | F192: * Referenced parent Order Type | G192: String(64) | H192: No | I192: enum=(BlanketOrder|Pull|MultiSrcPull|GenericOrder|BlanketRelease|DiscreteOrder|CustomerOrder|SchedAgreement) | J192: ssp.res.refd.order.type | L192: *,*.down | M192: Both | N192: VARCHAR(64)
A193: =A192+1 -> 189 | B193: RefdOrderNumber | C193: =C192+1 -> 189 | D193: Ref Order ID | E193: =E192+1 -> 189 | F193: * Referenced parent Order Number | G193: String(64) | H193: No | J193: ssp.res.refd.order.number | L193: *,*.down | M193: Both | N193: VARCHAR(64)
A194: =A193+1 -> 190 | B194: RefdOrderLineId | C194: =C193+1 -> 190 | D194: Ref Order Line ID | E194: =E193+1 -> 190 | F194: * Referenced parent Order Line Item Id | G194: Integer(19) | H194: No | J194: ssp.res.refd.order.line.id | L194: *,*.down | M194: Both | N194: NUMBER(19)
A195: =A194+1 -> 191 | B195: RefdOrderScheduleId | C195: =C194+1 -> 191 | D195: Ref Order Request ID | E195: =E194+1 -> 191 | F195: * Referenced parent Order Schedule Id | G195: Integer(19) | H195: No | J195: ssp.res.refd.order.schedule.id | K195: <%AsnLineItem.PoRequestScheduleId%> | L195: *,*.down | M195: Both | N195: NUMBER(19)
A196: =A195+1 -> 192 | B196: RefdOrderPromiseScheduleId | C196: =C195+1 -> 192 | D196: Ref Order Promise ID | E196: =E195+1 -> 192 | F196: * Referenced parent Order Promise Id | G196: Integer(19) | H196: No | J196: ssp.res.refd.order.promise.id | L196: *,*.down | M196: Both | N196: NUMBER(19)
A197: =A196+1 -> 193 | B197: FlexAttrStringLine1 | C197: =C196+1 -> 193 | D197: Flex String ASN Line 1 | E197: =E196+1 -> 193 | F197: * Project level configurable field for the allowed string length * Preconfigured to be updated in InsertOrUpdate | G197: String(255) | H197: No | J197: ssp.res.flex.attr.asn.line.string1 | L197: *,*.down | M197: Both | N197: VARCHAR(255)
A198: =A197+1 -> 194 | B198: FlexAttrStringLine2 | C198: =C197+1 -> 194 | D198: Flex String ASN Line 2 | E198: =E197+1 -> 194 | F198: * Project level configurable field for the allowed string length * Preconfigured to be updated in InsertOrUpdate | G198: String(255) | H198: No | J198: ssp.res.flex.attr.asn.line.string2 | L198: *,*.down | M198: Both | N198: VARCHAR(255)
A199: =A198+1 -> 195 | B199: FlexAttrStringLine3 | C199: =C198+1 -> 195 | D199: Flex String ASN Line 3 | E199: =E198+1 -> 195 | F199: * Project level configurable field for the allowed string length * Preconfigured to be updated in InsertOrUpdate | G199: String(255) | H199: No | J199: ssp.res.flex.attr.asn.line.string3 | L199: *,*.down | M199: Both | N199: VARCHAR(255)
A200: =A199+1 -> 196 | B200: FlexAttrStringLine4 | C200: =C199+1 -> 196 | D200: Flex String ASN Line 4 | E200: =E199+1 -> 196 | F200: * Project level configurable field for the allowed string length * Preconfigured to be updated in InsertOrUpdate | G200: String(128) | H200: No | J200: ssp.res.flex.attr.asn.line.string4 | L200: *,*.down | M200: Both | N200: VARCHAR(128)
A201: =A200+1 -> 197 | B201: FlexAttrStringLine5 | C201: =C200+1 -> 197 | D201: Flex String ASN Line 5 | E201: =E200+1 -> 197 | F201: * Project level configurable field for the allowed string length * Preconfigured to be updated in InsertOrUpdate | G201: String(128) | H201: No | J201: ssp.res.flex.attr.asn.line.string5 | L201: *,*.down | M201: Both | N201: VARCHAR(128)
A202: =A201+1 -> 198 | B202: FlexAttrStringLine6 | C202: =C201+1 -> 198 | D202: Flex String ASN Line 6 | E202: =E201+1 -> 198 | F202: * Project level configurable field for the allowed string length * Preconfigured to be updated in InsertOrUpdate | G202: String(128) | H202: No | J202: ssp.res.flex.attr.asn.line.string6 | L202: *,*.down | M202: Both | N202: VARCHAR(128)
A203: =A202+1 -> 199 | B203: FlexAttrStringLine7 | C203: =C202+1 -> 199 | D203: Flex String ASN Line 7 | E203: =E202+1 -> 199 | F203: * Project level configurable field for the allowed string length * Preconfigured to be updated in InsertOrUpdate | G203: String(64) | H203: No | J203: ssp.res.flex.attr.asn.line.string7 | L203: *,*.down | M203: Both | N203: VARCHAR(64)
A204: =A203+1 -> 200 | B204: FlexAttrStringLine8 | C204: =C203+1 -> 200 | D204: Flex String ASN Line 8 | E204: =E203+1 -> 200 | F204: * Project level configurable field for the allowed string length * Preconfigured to be updated in InsertOrUpdate | G204: String(64) | H204: No | J204: ssp.res.flex.attr.asn.line.string8 | L204: *,*.down | M204: Both | N204: VARCHAR(64)
A205: =A204+1 -> 201 | B205: FlexAttrStringLine9 | C205: =C204+1 -> 201 | D205: Flex String ASN Line 9 | E205: =E204+1 -> 201 | F205: * Project level configurable field for the allowed string length * Preconfigured to be updated in InsertOrUpdate | G205: String(64) | H205: No | J205: ssp.res.flex.attr.asn.line.string9 | L205: *,*.down | M205: Both | N205: VARCHAR(64)
...
